LICENSE.txt
README.md
setup.py
.eggs/README.txt
.eggs/setuptools_git-1.2-py2.7.egg
vakdocker/__init__.py
vakdocker/container.py
vakdocker/daemon.py
vakdocker.egg-info/PKG-INFO
vakdocker.egg-info/SOURCES.txt
vakdocker.egg-info/dependency_links.txt
vakdocker.egg-info/requires.txt
vakdocker.egg-info/top_level.txt
vakdocker/bin/vakdocker
vakdocker/utils/__init__.py
vakdocker/utils/network.py
vakdocker/utils/openssl_keys.py