Metadata-Version: 1.0
Name: vakdocker
Version: 0.3.8.dev0
Summary: Vaksana Utility to Manage Secure Docker
Home-page: http://vaksana.com/docker
Author: Pankaj Garg
Author-email: garg.pankaj83@gmail.com
License: PSF
Keywords: Vaksana
Platform: UNKNOWN
